risk_of_bias/__init__.py
risk_of_bias/cli.py
risk_of_bias/compare.py
risk_of_bias/config.py
risk_of_bias/export.py
risk_of_bias/human.py
risk_of_bias/prompts.py
risk_of_bias/run_framework.py
risk_of_bias/summary.py
risk_of_bias/visualisation.py
risk_of_bias/web.py
risk_of_bias-0.17.0.dist-info/licenses/LICENSE
risk_of_bias-0.17.0.dist-info/METADATA
risk_of_bias-0.17.0.dist-info/WHEEL
risk_of_bias-0.17.0.dist-info/entry_points.txt
risk_of_bias-0.17.0.dist-info/top_level.txt
risk_of_bias-0.17.0.dist-info/RECORD
