Metadata-Version: 2.4
Name: risk-of-bias
Version: 0.17.0
Summary: Software and AI for Risk of Bias assessment.
Author-email: Robert Luke <code@robertluke.net>
Project-URL: Homepage, https://github.com/rob-luke/risk-of-bias
Project-URL: Issues, https://github.com/rob-luke/risk-of-bias/issues
Requires-Python: >=3.12.0
License-File: LICENSE
Requires-Dist: pydantic>=2.11.4
Requires-Dist: pydantic-settings>=2.9.1
Requires-Dist: openai>=1.84.0
Requires-Dist: typer>=0.12.3
Requires-Dist: htpy>=25.6.2
Requires-Dist: pandas>=2.2.2
Requires-Dist: matplotlib>=3.9.0
Provides-Extra: dev
Requires-Dist: black>=25.1.0; extra == "dev"
Requires-Dist: mypy>=1.16.0; extra == "dev"
Requires-Dist: isort>=6.0.1; extra == "dev"
Requires-Dist: flake8>=7.2.0; extra == "dev"
Requires-Dist: pyright>=1.1.401; extra == "dev"
Requires-Dist: codespell>=2.4.1; extra == "dev"
Requires-Dist: pytest>=8.0.0; extra == "dev"
Requires-Dist: mkdocs-material>=9.6.14; extra == "dev"
Requires-Dist: mkdocstrings[python]>=0.29.1; extra == "dev"
Requires-Dist: python-semantic-release==7.33.3; extra == "dev"
Requires-Dist: pyinstaller>=6.14.1; extra == "dev"
Requires-Dist: pandas-stubs; extra == "dev"
Provides-Extra: web
Requires-Dist: fastapi>=0.111.0; extra == "web"
Requires-Dist: uvicorn>=0.29.0; extra == "web"
Requires-Dist: python-multipart>=0.0.9; extra == "web"
Provides-Extra: all
Requires-Dist: risk-of-bias[dev,web]; extra == "all"
Dynamic: license-file
